mycodebuddyproject/__init__.py
mycodebuddyproject/__main__.py
mycodebuddyproject/fun_facts.py
mycodebuddyproject/get_debug_tips.py
mycodebuddyproject/get_help.py
mycodebuddyproject/study_timer.py
mycodebuddyproject-0.1.4.dist-info/licenses/LICENSE
mycodebuddyproject-0.1.4.dist-info/METADATA
mycodebuddyproject-0.1.4.dist-info/WHEEL
mycodebuddyproject-0.1.4.dist-info/entry_points.txt
mycodebuddyproject-0.1.4.dist-info/top_level.txt
mycodebuddyproject-0.1.4.dist-info/RECORD
