Metadata-Version: 2.4
Name: mycodebuddyproject
Version: 0.1.4
Summary: An example of a package developed with pipenv, built with build using setuptools, uploaded to PyPI using twine, and distributed via pip.
Author-email: Melissa Kelly <mlk9103@nyu.edu>, Angel Serrano <ads8881@nyu.edu>, Aria Nguyen <ann9911@nyu.edu>, Siyu Lei <sl8839@nyu.edu>
License:                     GNU GENERAL PUBLIC LICENSE
Project-URL: Homepage, https://github.com/software-students-spring2025/3-python-package-float
Project-URL: Repository, https://github.com/software-students-spring2025/3-python-package-float.git
Project-URL: Bug Tracker, https://github.com/software-students-spring2025/3-python-package-float/issues
Keywords: python,package,build,tutorial
Classifier: Programming Language :: Python :: 3
Classifier: Intended Audience :: Education
Classifier: License :: OSI Approved :: GNU General Public License v3 (GPLv3)
Classifier: Operating System :: OS Independent
Requires-Python: >=3.7
License-File: LICENSE
Provides-Extra: dev
Requires-Dist: pytest; extra == "dev"
Dynamic: license-file
